{
  "slug": "kpi_threshold_template",
  "title": "KPI Threshold Templates",
  "kind": "object",
  "description": "A `kpi_threshold_template` is a set of predefined threshold values that you can apply to multiple KPIs.",
  "object_type": "kpi_threshold_template",
  "interface": "/itoa_interface",
  "endpoint": "/itoa_interface/kpi_threshold_template",
  "subordinate_objects": [],
  "attributes": [
    {
      "name": "title",
      "label": "title",
      "type": "string",
      "type_raw": "String",
      "required": true,
      "read_only": false,
      "description": "Name of this template.",
      "subordinate": null
    },
    {
      "name": "description",
      "label": "description",
      "type": "string",
      "type_raw": "String",
      "required": false,
      "read_only": false,
      "description": "Description of this particular template.",
      "subordinate": null
    },
    {
      "name": "adaptive_thresholding_training_window",
      "label": "adaptive_thresholding_training_window",
      "type": "string",
      "type_raw": "String",
      "required": false,
      "read_only": false,
      "description": "Earliest time for the adaptive threshold training algorithm to run over. The latest time is always `now`.",
      "subordinate": null
    },
    {
      "name": "time_variate_thresholds",
      "label": "time_variate_thresholds",
      "type": "boolean",
      "type_raw": "Boolean",
      "required": false,
      "read_only": false,
      "description": "If true, thresholds for alerts are pulled from time_variate_thresholds_specification.",
      "subordinate": null
    },
    {
      "name": "time_variate_thresholds_specification",
      "label": "time_variate_thresholds_specification",
      "type": "object",
      "type_raw": "Object",
      "required": false,
      "read_only": false,
      "description": "Data structure for time variate threshold specification.",
      "subordinate": null
    },
    {
      "name": "adaptive_thresholds_is_enabled",
      "label": "adaptive_thresholds_is_enabled",
      "type": "boolean",
      "type_raw": "Boolean",
      "required": false,
      "read_only": false,
      "description": "If true, adaptive thresholding is enabled for this KPI.",
      "subordinate": null
    },
    {
      "name": "sec_grp",
      "label": "sec_grp",
      "type": "string",
      "type_raw": "String",
      "required": false,
      "read_only": false,
      "description": "The team the object belongs to. This object can only belong to default_itsi_security_group (Global team).",
      "subordinate": null
    },
    {
      "name": "object_type",
      "label": "object_type",
      "type": "string",
      "type_raw": "String",
      "required": false,
      "read_only": true,
      "description": "Name of the object type.",
      "subordinate": null
    },
    {
      "name": "create_by",
      "label": "create_by",
      "type": "string",
      "type_raw": "String",
      "required": false,
      "read_only": true,
      "description": "The user who created this object.",
      "subordinate": null
    },
    {
      "name": "create_source",
      "label": "create_source",
      "type": "string",
      "type_raw": "String",
      "required": false,
      "read_only": true,
      "description": "The sourcetype initiating create. Has value `manual` for user-initiated creates. For internal use only.",
      "subordinate": null
    },
    {
      "name": "create_time",
      "label": "create_time",
      "type": "string",
      "type_raw": "String",
      "required": false,
      "read_only": true,
      "description": "Timestamp at the time of creation based on UTC time zone.",
      "subordinate": null
    },
    {
      "name": "mod_source",
      "label": "mod_source",
      "type": "string",
      "type_raw": "String",
      "required": false,
      "read_only": true,
      "description": "Sourcetype initiating modification. Has value `manual` for user-initiated modifications. For internal use only.",
      "subordinate": null
    },
    {
      "name": "mod_time",
      "label": "mod_time",
      "type": "string",
      "type_raw": "String",
      "required": false,
      "read_only": true,
      "description": "Timestamp of the last modification based on UTC time zone.",
      "subordinate": null
    },
    {
      "name": "_owner",
      "label": "_owner",
      "type": "string",
      "type_raw": "String",
      "required": false,
      "read_only": true,
      "description": "Splunk user `nobody`.",
      "subordinate": null
    },
    {
      "name": "_user",
      "label": "_user",
      "type": "string",
      "type_raw": "String",
      "required": false,
      "read_only": true,
      "description": "User who performed the most recent operation on this object.",
      "subordinate": null
    },
    {
      "name": "version",
      "label": "version",
      "type": "string",
      "type_raw": "String",
      "required": false,
      "read_only": true,
      "description": "The version of the object. Currently the same as the ITSI app version.",
      "subordinate": null
    }
  ]
}
